flask_sendgrid.py
Flask_SendGrid-0.7.1.dist-info/LICENSE
Flask_SendGrid-0.7.1.dist-info/METADATA
Flask_SendGrid-0.7.1.dist-info/WHEEL
Flask_SendGrid-0.7.1.dist-info/top_level.txt
Flask_SendGrid-0.7.1.dist-info/RECORD
