Metadata-Version: 1.1
Name: Flask-SendGrid
Version: 0.7.1
Summary: Adds SendGrid support to Flask applications
Home-page: http://github.com/frankv/flask-sendgrid
Author: Frank Valcarcel
Author-email: frank@cuttlesoft.com
License: MIT
Download-URL: https://github.com/frankv/flask-sendgrid/tarball/0.7.1
Keywords: Flask,SendGrid,email,smtp
Platform: any
Classifier: Development Status :: 3 - Alpha
Classifier: Environment :: Web Environment
Classifier: Intended Audience :: Developers
Classifier: License :: OSI Approved :: MIT License
Classifier: Operating System :: OS Independent
Classifier: Programming Language :: Python
Classifier: Topic :: Internet :: WWW/HTTP :: Dynamic Content
Classifier: Topic :: Software Development :: Libraries :: Python Modules
